<?xml version="1.0" encoding="utf-8"?>
<ArrayOfAssignment xmlns:xsi="http://www.w3.org/2001/XMLSchema-instance" xmlns:xsd="http://www.w3.org/2001/XMLSchema">
  <Assignment>
    <AssignmentId>1000</AssignmentId>
    <CallId>100000000</CallId>
    <VolunteerId>39764663</VolunteerId>
    <Begin>2025-01-29T20:25:22</Begin>
    <End>2025-01-29T20:31:22</End>
    <MyEndStatus>Completed</MyEndStatus>
  </Assignment>
  <Assignment>
    <AssignmentId>1001</AssignmentId>
    <CallId>100000001</CallId>
    <VolunteerId>14591550</VolunteerId>
    <Begin>2025-01-29T20:42:24</Begin>
    <End>2025-01-29T20:59:24</End>
    <MyEndStatus>Completed</MyEndStatus>
  </Assignment>
  <Assignment>
    <AssignmentId>1002</AssignmentId>
    <CallId>100000002</CallId>
    <VolunteerId>15038469</VolunteerId>
    <Begin>2025-01-29T20:48:30</Begin>
    <End>2025-01-29T20:52:30</End>
    <MyEndStatus>Completed</MyEndStatus>
  </Assignment>
  <Assignment>
    <AssignmentId>1003</AssignmentId>
    <CallId>100000003</CallId>
    <VolunteerId>36270284</VolunteerId>
    <Begin>2025-01-29T20:36:26</Begin>
    <End>2025-01-29T20:40:26</End>
    <MyEndStatus>Completed</MyEndStatus>
  </Assignment>
  <Assignment>
    <AssignmentId>1004</AssignmentId>
    <CallId>100000004</CallId>
    <VolunteerId>38363071</VolunteerId>
    <Begin>2025-01-29T20:42:21</Begin>
    <End>2025-01-29T20:46:21</End>
    <MyEndStatus>Completed</MyEndStatus>
  </Assignment>
  <Assignment>
    <AssignmentId>1005</AssignmentId>
    <CallId>100000005</CallId>
    <VolunteerId>32382925</VolunteerId>
    <Begin>2025-01-29T20:21:32</Begin>
    <End>2025-01-29T20:26:32</End>
    <MyEndStatus>Completed</MyEndStatus>
  </Assignment>
  <Assignment>
    <AssignmentId>1006</AssignmentId>
    <CallId>100000006</CallId>
    <VolunteerId>29206115</VolunteerId>
    <Begin>2025-01-29T20:33:11</Begin>
    <End>2025-01-29T20:45:11</End>
    <MyEndStatus>Completed</MyEndStatus>
  </Assignment>
  <Assignment>
    <AssignmentId>1007</AssignmentId>
    <CallId>100000007</CallId>
    <VolunteerId>38882785</VolunteerId>
    <Begin>2025-01-29T20:24:14</Begin>
    <End>2025-01-29T20:26:14</End>
    <MyEndStatus>Completed</MyEndStatus>
  </Assignment>
  <Assignment>
    <AssignmentId>1008</AssignmentId>
    <CallId>100000008</CallId>
    <VolunteerId>13008886</VolunteerId>
    <Begin>2025-01-29T20:38:08</Begin>
    <End>2025-01-29T21:31:01</End>
    <MyEndStatus>Expired</MyEndStatus>
  </Assignment>
  <Assignment>
    <AssignmentId>1009</AssignmentId>
    <CallId>100000009</CallId>
    <VolunteerId>13495118</VolunteerId>
    <Begin>2025-01-29T20:44:26</Begin>
    <End>2025-01-29T20:58:26</End>
    <MyEndStatus>Completed</MyEndStatus>
  </Assignment>
  <Assignment>
    <AssignmentId>1010</AssignmentId>
    <CallId>100000010</CallId>
    <VolunteerId>33594684</VolunteerId>
    <Begin>2025-01-29T20:29:17</Begin>
    <End>2025-01-29T20:32:17</End>
    <MyEndStatus>Completed</MyEndStatus>
  </Assignment>
  <Assignment>
    <AssignmentId>1011</AssignmentId>
    <CallId>100000011</CallId>
    <VolunteerId>25018433</VolunteerId>
    <Begin>2025-01-29T20:18:01</Begin>
    <End>2025-01-29T20:29:01</End>
    <MyEndStatus>Completed</MyEndStatus>
  </Assignment>
  <Assignment>
    <AssignmentId>1012</AssignmentId>
    <CallId>100000012</CallId>
    <VolunteerId>13306271</VolunteerId>
    <Begin>2025-01-29T20:39:54</Begin>
    <End>2025-01-29T20:46:54</End>
    <MyEndStatus>Completed</MyEndStatus>
  </Assignment>
  <Assignment>
    <AssignmentId>1013</AssignmentId>
    <CallId>100000013</CallId>
    <VolunteerId>14105036</VolunteerId>
    <Begin>2025-01-29T20:21:46</Begin>
    <End>2025-01-29T20:22:46</End>
    <MyEndStatus>Completed</MyEndStatus>
  </Assignment>
  <Assignment>
    <AssignmentId>1014</AssignmentId>
    <CallId>100000014</CallId>
    <VolunteerId>14559919</VolunteerId>
    <Begin>2025-01-29T20:36:37</Begin>
    <End>2025-01-29T20:42:37</End>
    <MyEndStatus>Completed</MyEndStatus>
  </Assignment>
  <Assignment>
    <AssignmentId>1015</AssignmentId>
    <CallId>100000015</CallId>
    <VolunteerId>26719308</VolunteerId>
    <Begin>2025-01-29T21:37:44</Begin>
    <End>2025-01-29T21:55:44</End>
    <MyEndStatus>Completed</MyEndStatus>
  </Assignment>
  <Assignment>
    <AssignmentId>1016</AssignmentId>
    <CallId>100000016</CallId>
    <VolunteerId>28558066</VolunteerId>
    <Begin>2025-01-29T21:35:47</Begin>
    <End>2025-01-29T22:02:01</End>
    <MyEndStatus>Expired</MyEndStatus>
  </Assignment>
  <Assignment>
    <AssignmentId>1017</AssignmentId>
    <CallId>100000017</CallId>
    <VolunteerId>39764663</VolunteerId>
    <Begin>2025-01-29T21:32:35</Begin>
    <End>2025-01-29T21:50:01</End>
    <MyEndStatus>Expired</MyEndStatus>
  </Assignment>
  <Assignment>
    <AssignmentId>1018</AssignmentId>
    <CallId>100000018</CallId>
    <VolunteerId>14591550</VolunteerId>
    <Begin>2025-01-29T21:36:09</Begin>
    <End>2025-01-29T21:38:09</End>
    <MyEndStatus>Completed</MyEndStatus>
  </Assignment>
  <Assignment>
    <AssignmentId>1019</AssignmentId>
    <CallId>100000019</CallId>
    <VolunteerId>15038469</VolunteerId>
    <Begin>2025-01-29T21:36:28</Begin>
    <End>2025-01-29T21:49:28</End>
    <MyEndStatus>Completed</MyEndStatus>
  </Assignment>
  <Assignment>
    <AssignmentId>1020</AssignmentId>
    <CallId>100000020</CallId>
    <VolunteerId>36270284</VolunteerId>
    <Begin>2025-01-29T21:47:47</Begin>
    <End>2025-01-29T21:47:47</End>
    <MyEndStatus>Completed</MyEndStatus>
  </Assignment>
  <Assignment>
    <AssignmentId>1021</AssignmentId>
    <CallId>100000021</CallId>
    <VolunteerId>38363071</VolunteerId>
    <Begin>2025-01-29T21:19:53</Begin>
    <End>2025-01-29T21:26:53</End>
    <MyEndStatus>Completed</MyEndStatus>
  </Assignment>
  <Assignment>
    <AssignmentId>1022</AssignmentId>
    <CallId>100000022</CallId>
    <VolunteerId>32382925</VolunteerId>
    <Begin>2025-01-29T21:28:31</Begin>
    <End>2025-01-29T21:33:31</End>
    <MyEndStatus>Completed</MyEndStatus>
  </Assignment>
  <Assignment>
    <AssignmentId>1023</AssignmentId>
    <CallId>100000023</CallId>
    <VolunteerId>29206115</VolunteerId>
    <Begin>2025-01-29T21:29:55</Begin>
    <End>2025-01-29T21:30:55</End>
    <MyEndStatus>Completed</MyEndStatus>
  </Assignment>
  <Assignment>
    <AssignmentId>1024</AssignmentId>
    <CallId>100000024</CallId>
    <VolunteerId>38882785</VolunteerId>
    <Begin>2025-01-29T21:32:45</Begin>
    <End>2025-01-29T21:52:45</End>
    <MyEndStatus>Completed</MyEndStatus>
  </Assignment>
  <Assignment>
    <AssignmentId>1025</AssignmentId>
    <CallId>100000025</CallId>
    <VolunteerId>13008886</VolunteerId>
    <Begin>2025-01-29T21:44:41</Begin>
    <End>2025-01-29T21:48:41</End>
    <MyEndStatus>Completed</MyEndStatus>
  </Assignment>
  <Assignment>
    <AssignmentId>1026</AssignmentId>
    <CallId>100000026</CallId>
    <VolunteerId>13495118</VolunteerId>
    <Begin>2025-01-29T21:42:02</Begin>
    <End>2025-01-29T21:59:02</End>
    <MyEndStatus>Completed</MyEndStatus>
  </Assignment>
  <Assignment>
    <AssignmentId>1027</AssignmentId>
    <CallId>100000027</CallId>
    <VolunteerId>33594684</VolunteerId>
    <Begin>2025-01-29T21:47:10</Begin>
    <End>2025-01-29T21:49:10</End>
    <MyEndStatus>Completed</MyEndStatus>
  </Assignment>
  <Assignment>
    <AssignmentId>1028</AssignmentId>
    <CallId>100000028</CallId>
    <VolunteerId>25018433</VolunteerId>
    <Begin>2025-01-29T21:26:13</Begin>
    <End>2025-01-29T22:03:13</End>
    <MyEndStatus>Completed</MyEndStatus>
  </Assignment>
  <Assignment>
    <AssignmentId>1029</AssignmentId>
    <CallId>100000029</CallId>
    <VolunteerId>13306271</VolunteerId>
    <Begin>2025-01-29T21:32:06</Begin>
    <End>2025-01-29T21:43:06</End>
    <MyEndStatus>Completed</MyEndStatus>
  </Assignment>
  <Assignment>
    <AssignmentId>1030</AssignmentId>
    <CallId>100000030</CallId>
    <VolunteerId>14105036</VolunteerId>
    <Begin>2025-01-30T01:04:04</Begin>
    <End>2025-01-30T01:07:04</End>
    <MyEndStatus>SelfCancelled</MyEndStatus>
  </Assignment>
  <Assignment>
    <AssignmentId>1031</AssignmentId>
    <CallId>100000031</CallId>
    <VolunteerId>14559919</VolunteerId>
    <Begin>2025-01-30T00:10:23</Begin>
    <End>2025-01-30T00:11:23</End>
    <MyEndStatus>SelfCancelled</MyEndStatus>
  </Assignment>
  <Assignment>
    <AssignmentId>1032</AssignmentId>
    <CallId>100000032</CallId>
    <VolunteerId>26719308</VolunteerId>
    <Begin>2025-01-29T23:47:21</Begin>
    <End>2025-01-29T23:56:21</End>
    <MyEndStatus>ManagerCancelled</MyEndStatus>
  </Assignment>
  <Assignment>
    <AssignmentId>1033</AssignmentId>
    <CallId>100000033</CallId>
    <VolunteerId>28558066</VolunteerId>
    <Begin>2025-01-30T00:34:35</Begin>
    <End>2025-01-30T00:43:35</End>
    <MyEndStatus>SelfCancelled</MyEndStatus>
  </Assignment>
  <Assignment>
    <AssignmentId>1034</AssignmentId>
    <CallId>100000034</CallId>
    <VolunteerId>39764663</VolunteerId>
    <Begin>2025-01-29T23:21:04</Begin>
    <End>2025-01-29T23:26:04</End>
    <MyEndStatus>ManagerCancelled</MyEndStatus>
  </Assignment>
  <Assignment>
    <AssignmentId>1035</AssignmentId>
    <CallId>100000035</CallId>
    <VolunteerId>14591550</VolunteerId>
    <Begin>2025-01-29T23:56:06</Begin>
    <End>2025-01-30T00:02:06</End>
    <MyEndStatus>SelfCancelled</MyEndStatus>
  </Assignment>
  <Assignment>
    <AssignmentId>1036</AssignmentId>
    <CallId>100000036</CallId>
    <VolunteerId>15038469</VolunteerId>
    <Begin>2025-01-29T23:55:04</Begin>
    <End>2025-01-30T00:01:04</End>
    <MyEndStatus>ManagerCancelled</MyEndStatus>
  </Assignment>
  <Assignment>
    <AssignmentId>1037</AssignmentId>
    <CallId>100000037</CallId>
    <VolunteerId>36270284</VolunteerId>
    <Begin>2025-01-30T00:24:00</Begin>
    <End>2025-01-30T00:33:00</End>
    <MyEndStatus>SelfCancelled</MyEndStatus>
  </Assignment>
  <Assignment>
    <AssignmentId>1038</AssignmentId>
    <CallId>100000038</CallId>
    <VolunteerId>38363071</VolunteerId>
    <Begin>2025-01-29T23:40:02</Begin>
    <End>2025-01-29T23:40:02</End>
    <MyEndStatus>ManagerCancelled</MyEndStatus>
  </Assignment>
  <Assignment>
    <AssignmentId>1039</AssignmentId>
    <CallId>100000039</CallId>
    <VolunteerId>32382925</VolunteerId>
    <Begin>2025-01-29T23:23:31</Begin>
    <End>2025-01-29T23:29:31</End>
    <MyEndStatus>SelfCancelled</MyEndStatus>
  </Assignment>
  <Assignment>
    <AssignmentId>1040</AssignmentId>
    <CallId>100000030</CallId>
    <VolunteerId>38363071</VolunteerId>
    <Begin>2025-01-30T01:32:01</Begin>
    <End xsi:nil="true" />
    <MyEndStatus xsi:nil="true" />
  </Assignment>
  <Assignment>
    <AssignmentId>1041</AssignmentId>
    <CallId>100000031</CallId>
    <VolunteerId>32382925</VolunteerId>
    <Begin>2025-01-30T00:38:01</Begin>
    <End xsi:nil="true" />
    <MyEndStatus xsi:nil="true" />
  </Assignment>
  <Assignment>
    <AssignmentId>1042</AssignmentId>
    <CallId>100000032</CallId>
    <VolunteerId>29206115</VolunteerId>
    <Begin>2025-01-30T00:05:01</Begin>
    <End xsi:nil="true" />
    <MyEndStatus xsi:nil="true" />
  </Assignment>
  <Assignment>
    <AssignmentId>1043</AssignmentId>
    <CallId>100000033</CallId>
    <VolunteerId>38882785</VolunteerId>
    <Begin>2025-01-30T00:59:01</Begin>
    <End>2025-01-30T01:08:01</End>
    <MyEndStatus>Completed</MyEndStatus>
  </Assignment>
  <Assignment>
    <AssignmentId>1044</AssignmentId>
    <CallId>100000034</CallId>
    <VolunteerId>13008886</VolunteerId>
    <Begin>2025-01-29T23:43:01</Begin>
    <End xsi:nil="true" />
    <MyEndStatus xsi:nil="true" />
  </Assignment>
  <Assignment>
    <AssignmentId>1045</AssignmentId>
    <CallId>100000035</CallId>
    <VolunteerId>13495118</VolunteerId>
    <Begin>2025-01-30T00:12:01</Begin>
    <End xsi:nil="true" />
    <MyEndStatus xsi:nil="true" />
  </Assignment>
  <Assignment>
    <AssignmentId>1046</AssignmentId>
    <CallId>100000036</CallId>
    <VolunteerId>33594684</VolunteerId>
    <Begin>2025-01-30T00:23:01</Begin>
    <End xsi:nil="true" />
    <MyEndStatus xsi:nil="true" />
  </Assignment>
  <Assignment>
    <AssignmentId>1047</AssignmentId>
    <CallId>100000037</CallId>
    <VolunteerId>25018433</VolunteerId>
    <Begin>2025-01-30T00:38:01</Begin>
    <End xsi:nil="true" />
    <MyEndStatus xsi:nil="true" />
  </Assignment>
  <Assignment>
    <AssignmentId>1048</AssignmentId>
    <CallId>100000038</CallId>
    <VolunteerId>13306271</VolunteerId>
    <Begin>2025-01-30T00:05:01</Begin>
    <End xsi:nil="true" />
    <MyEndStatus xsi:nil="true" />
  </Assignment>
  <Assignment>
    <AssignmentId>1049</AssignmentId>
    <CallId>100000039</CallId>
    <VolunteerId>14105036</VolunteerId>
    <Begin>2025-01-29T23:39:01</Begin>
    <End>2025-01-30T00:25:01</End>
    <MyEndStatus>Expired</MyEndStatus>
  </Assignment>
</ArrayOfAssignment>